Metadata-Version: 2.1
Name: senseiv2test-aliFrancis
Version: 1.0
Summary: Sensor Independent Cloud and Shadow Masking with Partial Labels and Multimodal Inputs
Author-Email: Alistair Francis <alistair.m.francis@gmail.com>
Classifier: Programming Language :: Python :: 3
Classifier: License :: OSI Approved :: GNU General Public License v3 (GPLv3)
Classifier: Operating System :: OS Independent
Project-URL: Homepage, https://github.com/aliFrancis/SEnSeIv2
Project-URL: Issues, https://github.com/aliFrancis/SEnSeIv2/issues
Requires-Python: >=3.9
